__init__.py
aeronist.py
aeronist-0.0.3.dist-info/LICENSE
aeronist-0.0.3.dist-info/METADATA
aeronist-0.0.3.dist-info/WHEEL
aeronist-0.0.3.dist-info/top_level.txt
aeronist-0.0.3.dist-info/RECORD
